<Defs xmlns:xsi="http://www.w3.org/2001/XMLSchema-instance" xsi:noNamespaceSchemaLocation="../../Schemas/AspectDef.xsd">

    <Pawnmorph.AspectDef>
        <defName>PMM_ConversionAspect</defName>
        <label>TODO</label>
        <aspectType>PawnmorpherMutagenesis.Aspects.Conversion</aspectType>
        <description>TODO</description>
        <transferToAnimal>true</transferToAnimal>
		<stages>
			<li>
				<label>TODO conversion aspect</label>
				<description>TODO.</description>
			</li>
		</stages>
    </Pawnmorph.AspectDef>
</Defs>